rio_stac/__init__.py
rio_stac/stac.py
rio_stac/scripts/__init__.py
rio_stac/scripts/cli.py
rio_stac-0.11.2.dist-info/entry_points.txt
rio_stac-0.11.2.dist-info/licenses/LICENSE
rio_stac-0.11.2.dist-info/WHEEL
rio_stac-0.11.2.dist-info/METADATA
rio_stac-0.11.2.dist-info/RECORD
