Metadata-Version: 2.4
Name: rio-stac
Version: 0.11.2
Summary: Create STAC Items from raster datasets.
Author-email: Vincent Sarago <vincent@developmentseed.com>
Requires-Python: >=3.9
Classifier: Intended Audience :: Information Technology
Classifier: Intended Audience :: Science/Research
Classifier: License :: OSI Approved :: BSD License
Classifier: Programming Language :: Python :: 3.9
Classifier: Programming Language :: Python :: 3.10
Classifier: Programming Language :: Python :: 3.11
Classifier: Programming Language :: Python :: 3.12
Classifier: Programming Language :: Python :: 3.13
Classifier: Topic :: Scientific/Engineering :: GIS
License-File: LICENSE
Requires-Dist: rasterio>=1.0,!=1.4.2
Requires-Dist: pystac>=1.0.0,<2.0.0
Requires-Dist: pre-commit ; extra == "dev"
Requires-Dist: bump-my-version ; extra == "dev"
Requires-Dist: mkdocs ; extra == "docs"
Requires-Dist: mkdocs-material ; extra == "docs"
Requires-Dist: mkdocs-jupyter ; extra == "docs"
Requires-Dist: griffe-inherited-docstrings>=1.0.0 ; extra == "docs"
Requires-Dist: mkdocstrings[python]>=0.25.1 ; extra == "docs"
Requires-Dist: pygments ; extra == "docs"
Requires-Dist: pytest ; extra == "test"
Requires-Dist: pytest-cov ; extra == "test"
Requires-Dist: requests ; extra == "test"
Requires-Dist: pystac[validation]>=1.0.0,<2.0.0 ; extra == "test"
Project-URL: Documentation, https://developmentseed.org/rio-stac/
Project-URL: Source, https://github.com/developmentseed/rio-stac
Provides-Extra: dev
Provides-Extra: docs
Provides-Extra: test
